{
	"$schema": "http://json-schema.org/draft-07/schema#",
	"description": "JSON Schema generated by XMLSpy v2021 (x64) (http://www.altova.com)",
	"type": "object",
	"properties": {
		"uid": {
			"type": "string",
			"maxLength": 36
		},
		"type": {
			"type": "string",
			"enum": [
				"OTHER",
				"RFID"
			]
		},
		"auth_id": {
			"type": "string",
			"maxLength": 36
		},
		"visual_number": {
			"type": "string",
			"maxLength": 64
		},
		"issuer": {
			"type": "string",
			"maxLength": 64
		},
		"valid": {
			"type": "boolean"
		},
		"whitelist": {
			"type": "string",
			"enum": [
				"NEVER",
				"ALLOWED_OFFLINE",
				"ALLOWED",
				"ALWAYS"
			]
		},
		"language": {
			"type": "string",
			"maxLength": 2
		},
		"last_updated": {
			"$ref": "#/definitions/DateTime"
		}
	},
	"additionalProperties": true
}